codeprompt/__init__.py
codeprompt/__main__.py
llfmt/__init__.py
llfmt/__main__.py
llfmt-2024.1.23.dist-info/LICENSE
llfmt-2024.1.23.dist-info/METADATA
llfmt-2024.1.23.dist-info/WHEEL
llfmt-2024.1.23.dist-info/entry_points.txt
llfmt-2024.1.23.dist-info/top_level.txt
llfmt-2024.1.23.dist-info/RECORD
